benford/__init__.py
benford/benford.py
benford/checks.py
benford/constants.py
benford/expected.py
benford/reports.py
benford/stats.py
benford/utils.py
benford/viz.py
benford_py-0.5.0.dist-info/LICENSE.txt
benford_py-0.5.0.dist-info/METADATA
benford_py-0.5.0.dist-info/WHEEL
benford_py-0.5.0.dist-info/top_level.txt
benford_py-0.5.0.dist-info/RECORD
