Metadata-Version: 2.1
Name: benford-py
Version: 0.5.0
Summary: A library for testing data sets with Bendford's Law
Home-page: https://github.com/milcent/benford_py
Author: Marcel Milcent
Author-email: marcelmilcent@gmail.com
License: BSD 3-Clause
Download-URL: https://github.com/milcent/benford_py/archive/v0.5.0.tar.gz
Platform: UNKNOWN
Classifier: Programming Language :: Python :: 3
Classifier: License :: OSI Approved :: BSD License
Classifier: Natural Language :: English
Classifier: Operating System :: OS Independent
Classifier: Development Status :: 3 - Alpha
Classifier: Intended Audience :: Financial and Insurance Industry
Classifier: Intended Audience :: Science/Research
Classifier: Intended Audience :: Education
Classifier: Intended Audience :: Other Audience
Classifier: Topic :: Office/Business :: Financial :: Accounting
Classifier: Topic :: Scientific/Engineering :: Mathematics
License-File: LICENSE.txt
Requires-Dist: pandas
Requires-Dist: numpy
Requires-Dist: matplotlib
